{
  "id": "chrysospalax-trevelyani",
  "name": "Giant golden mole",
  "scientificName": "Chrysospalax trevelyani",
  "wikibase_item": "Q1765489",
  "taxonomy": {
    "taxonRank": {
      "entity-type": "item",
      "numeric-id": 7432,
      "id": "Q7432"
    },
    "parentTaxon": {
      "entity-type": "item",
      "numeric-id": 593921,
      "id": "Q593921"
    }
  },
  "source": {
    "wikidata": "https://www.wikidata.org/wiki/Q1765489",
    "wikipedia": "https://en.wikipedia.org/wiki/Giant_golden_mole"
  },
  "lastUpdated": "2025-12-17",
  "description": "The giant golden mole is a small mammal found in Africa. At 23 centimetres (9.1 in) in length, it is the largest of the golden mole species. This mole has dark, glossy brown fur; the name golden comes from the Greek word for green-gold, also the source of the name of the family, Chrysochloridae.",
  "image": "https://upload.wikimedia.org/wikipedia/commons/3/38/Em_-_Chrysospalax_trevelyani_-_2.jpg",
  "_score": 1
}