{
  "id": "funambulus-pucheranii",
  "name": "Funambulus pucheranii",
  "scientificName": "Funambulus pucheranii",
  "wikibase_item": "Q19674513",
  "taxonomy": {
    "taxonRank": {
      "entity-type": "item",
      "numeric-id": 7432,
      "id": "Q7432"
    },
    "parentTaxon": {
      "entity-type": "item",
      "numeric-id": 1004346,
      "id": "Q1004346"
    }
  },
  "source": {
    "wikidata": "https://www.wikidata.org/wiki/Q19674513"
  },
  "lastUpdated": "2025-12-17",
  "_rejectReasons": [
    "no_description",
    "no_wikipedia"
  ]
}