{
  "id": "genetta-grantii",
  "name": "Genetta grantii",
  "scientificName": "Genetta grantii",
  "wikibase_item": "Q41083657",
  "taxonomy": {
    "taxonRank": {
      "entity-type": "item",
      "numeric-id": 7432,
      "id": "Q7432"
    },
    "parentTaxon": {
      "entity-type": "item",
      "numeric-id": 43221,
      "id": "Q43221"
    }
  },
  "source": {
    "wikidata": "https://www.wikidata.org/wiki/Q41083657"
  },
  "lastUpdated": "2025-12-17",
  "_rejectReasons": [
    "no_description",
    "no_wikipedia"
  ]
}