{
  "id": "gerbillus-dasyurus",
  "name": "Wagnerís gerbil",
  "scientificName": "Gerbillus dasyurus",
  "wikibase_item": "Q25677062",
  "taxonomy": {
    "taxonRank": {
      "entity-type": "item",
      "numeric-id": 7432,
      "id": "Q7432"
    },
    "parentTaxon": {
      "entity-type": "item",
      "numeric-id": 517079,
      "id": "Q517079"
    }
  },
  "source": {
    "wikidata": "https://www.wikidata.org/wiki/Q25677062"
  },
  "lastUpdated": "2025-12-17",
  "_rejectReasons": [
    "no_description",
    "no_wikipedia"
  ]
}