{
  "id": "mormopterus-doriae",
  "name": "Sumatran Mastiff Bat",
  "scientificName": "Mormopterus doriae",
  "wikibase_item": "Q1831464",
  "taxonomy": {
    "taxonRank": {
      "entity-type": "item",
      "numeric-id": 7432,
      "id": "Q7432"
    },
    "parentTaxon": {
      "entity-type": "item",
      "numeric-id": 2579356,
      "id": "Q2579356"
    }
  },
  "source": {
    "wikidata": "https://www.wikidata.org/wiki/Q1831464",
    "wikipedia": "https://en.wikipedia.org/wiki/Sumatran_mastiff_bat"
  },
  "lastUpdated": "2025-12-17",
  "description": "The Sumatran mastiff bat is a species of bat in the family Molossidae, the free-tailed bats. It is only known from Sumatra in Indonesia. It was described in 1907 and has not been recorded since.",
  "image": null,
  "_score": 0
}