{
  "id": "scaptonyx-fusicaudus",
  "name": "Long-tailed Mole",
  "scientificName": "Scaptonyx fusicaudus",
  "wikibase_item": "Q786314",
  "taxonomy": {
    "taxonRank": {
      "entity-type": "item",
      "numeric-id": 7432,
      "id": "Q7432"
    },
    "parentTaxon": {
      "entity-type": "item",
      "numeric-id": 15402209,
      "id": "Q15402209"
    }
  },
  "source": {
    "wikidata": "https://www.wikidata.org/wiki/Q786314",
    "wikipedia": "https://en.wikipedia.org/wiki/Long-tailed_mole"
  },
  "lastUpdated": "2025-12-17",
  "description": "The long-tailed mole is a species of mole in the family Talpidae. It is found in China, Vietnam and Myanmar.",
  "image": "https://upload.wikimedia.org/wikipedia/commons/0/04/Long-tailed_mole.jpg",
  "_score": 1
}