{
  "id": "sturnira-thomasi",
  "name": "Thomas's yellow-shouldered bat",
  "scientificName": "Sturnira thomasi",
  "wikibase_item": "Q1593200",
  "taxonomy": {
    "taxonRank": {
      "entity-type": "item",
      "numeric-id": 7432,
      "id": "Q7432"
    },
    "parentTaxon": {
      "entity-type": "item",
      "numeric-id": 11950402,
      "id": "Q11950402"
    }
  },
  "source": {
    "wikidata": "https://www.wikidata.org/wiki/Q1593200",
    "wikipedia": "https://en.wikipedia.org/wiki/Sturnira_angeli"
  },
  "lastUpdated": "2025-12-17",
  "description": "Sturnira angeli, also known as the Guadeloupe yellow-shouldered bat or Angel's yellow-shouldered bat, is a species of bat in the family Phyllostomidae. It is endemic to the Lesser Antilles. As of 2018 it is listed as near threatened by the IUCN.",
  "image": null
}